setup.py
bin/search_engine_spider
search_engine_spider/__init__.py
search_engine_spider/config.py
search_engine_spider/search_engine_manager.py
search_engine_spider.egg-info/PKG-INFO
search_engine_spider.egg-info/SOURCES.txt
search_engine_spider.egg-info/dependency_links.txt
search_engine_spider.egg-info/requires.txt
search_engine_spider.egg-info/top_level.txt
search_engine_spider/data/user_agents.txt
search_engine_spider/search_engine/__init__.py
search_engine_spider/search_engine/bing.py
search_engine_spider/search_engine/google.py
search_engine_spider/search_engine/search_engine.py
search_engine_spider/search_engine/data/google.txt