Metadata-Version: 1.0
Name: search-engine-spider
Version: 0.1.8
Summary: A search engine spider
Home-page: UNKNOWN
Author: izhengzhixian
Author-email: izhengzhixian@gmail.com
License: UNKNOWN
Platform: any
